lektor_html_pretify.py
lektor_html_pretify-2.0.0.dist-info/LICENCE
lektor_html_pretify-2.0.0.dist-info/METADATA
lektor_html_pretify-2.0.0.dist-info/WHEEL
lektor_html_pretify-2.0.0.dist-info/entry_points.txt
lektor_html_pretify-2.0.0.dist-info/top_level.txt
lektor_html_pretify-2.0.0.dist-info/RECORD
