Metadata-Version: 2.1
Name: lektor-html-pretify
Version: 2.0.0
Summary: Lektor Plugin to pretify your HTML DOM using BeautifulSoup
Home-page: https://github.com/chaos-bodensee/lektor-html-pretify
Author: L3D
Author-email: l3d@c3woc.de
License: MIT
Keywords: Lektor plugin
Classifier: Framework :: Lektor
Classifier: Environment :: Plugins
License-File: LICENCE
Requires-Dist: bs4
